reportcreater/__init__.py
reportcreater/__main__.py
reportcreater/proc.py
reportcreater-0.1.0.dist-info/METADATA
reportcreater-0.1.0.dist-info/WHEEL
reportcreater-0.1.0.dist-info/entry_points.txt
reportcreater-0.1.0.dist-info/top_level.txt
reportcreater-0.1.0.dist-info/RECORD
